city_scrapers_sentry/__init__.py
city_scrapers_sentry/extensions.py
city_scrapers_sentry/utils.py
city_scrapers_sentry-1.0.0a4.dist-info/LICENSE
city_scrapers_sentry-1.0.0a4.dist-info/METADATA
city_scrapers_sentry-1.0.0a4.dist-info/WHEEL
city_scrapers_sentry-1.0.0a4.dist-info/top_level.txt
city_scrapers_sentry-1.0.0a4.dist-info/RECORD
