Metadata-Version: 2.1
Name: city-scrapers-sentry
Version: 1.0.0a4
Summary: Scrapy extension that logs errors to Sentry
Author-email: City Bureau <documenters@citybureau.org>
License: BSD
Classifier: Programming Language :: Python
Classifier: Programming Language :: Python :: 3
Classifier: License :: OSI Approved :: BSD License
Classifier: Operating System :: OS Independent
Classifier: Development Status :: 3 - Alpha
Classifier: Intended Audience :: Developers
Classifier: Environment :: Console
Classifier: Topic :: Software Development :: Libraries :: Application Frameworks
Classifier: Topic :: Software Development :: Libraries :: Python Modules
Classifier: Topic :: Internet :: WWW/HTTP
Requires-Python: >=3.9
License-File: LICENSE
Requires-Dist: scrapy >=2.0
Requires-Dist: sentry-sdk >=1.0.0
